django_page_visibility/README.md
django_page_visibility/RELEASE_NOTES.md
django_page_visibility/VERSION
django_page_visibility/__init__.py
django_page_visibility/__pycache__/__init__.cpython-36.pyc
django_page_visibility/templatetags/page_visibility.py
django_page_visibility/templatetags/__pycache__/django_page_visibility.cpython-36.pyc
django_page_visibility/templatetags/__pycache__/page_visibility.cpython-36.pyc
django_page_visibility-0.3.0.dist-info/LICENSE
django_page_visibility-0.3.0.dist-info/METADATA
django_page_visibility-0.3.0.dist-info/WHEEL
django_page_visibility-0.3.0.dist-info/top_level.txt
django_page_visibility-0.3.0.dist-info/RECORD
