Metadata-Version: 2.1
Name: django-page-visibility
Version: 0.3.0
Summary: Implements a function to test whether a given url is currently visible to a given user.
Home-page: https://github.com/quadrant-newmedia/django_page_visibility
Author: Alex Fischer
Author-email: alex@quadrant.net
License: UNKNOWN
Platform: UNKNOWN
Classifier: Programming Language :: Python :: 3
Classifier: License :: OSI Approved :: MIT License
Classifier: Operating System :: OS Independent
Requires-Python: >=3.7
Requires-Dist: Django (<6,>=3)
